curse_get/downloader.py
curse_get-1.0.0.dist-info/LICENSE
curse_get-1.0.0.dist-info/METADATA
curse_get-1.0.0.dist-info/WHEEL
curse_get-1.0.0.dist-info/entry_points.txt
curse_get-1.0.0.dist-info/top_level.txt
curse_get-1.0.0.dist-info/RECORD
