Metadata-Version: 2.1
Name: curse-get
Version: 1.0.0
Summary: Minecraft CurseForge API mod downloader
Author-email: Adam Charvát <adam.charvat@post.cz>
License: MIT License
Project-URL: Homepage, https://github.com/Skulaurun/curse-get
Project-URL: Bug Tracker, https://github.com/Skulaurun/curse-get/issues
Classifier: Programming Language :: Python :: 3
Classifier: License :: OSI Approved :: MIT License
Classifier: Operating System :: OS Independent
Requires-Python: >=3.7
License-File: LICENSE
Requires-Dist: requests (>=2.28.1)
